{"agent_type": "GridActorCriticLookaheadDecisionMaker", "preprocess_function": "grid_and_coverage_action_count_pre_process_input_compact_karel_markerbitmap", "network": "GridActionValueHandmadeFeaturesNetwork", "network_params": {"cnn_layer_sizes": [[64, 3, 1, 1, 1], [64, 3, 1, 1, 1], [64, 3, 1, 1, 1]], "pooling_layers_sizes": [[2, 2, 1, 0], [2, 2, 1, 0], [2, 2, 1, 0]], "latent_layer_sizes": [1024, 512, 256, 128, 32], "input_size": {"grid": [14, 16, 16], "features": 12}, "append_features": true, "decision_layers": [8], "output_size": 1}}